aiompd/__init__.py
aiompd/client.py
aiompd/helpers.py
aiompd/playlists.py
aiompd/protocol.py
aiompd/types.py
aiompd-0.4.0.dist-info/DESCRIPTION.rst
aiompd-0.4.0.dist-info/METADATA
aiompd-0.4.0.dist-info/RECORD
aiompd-0.4.0.dist-info/WHEEL
aiompd-0.4.0.dist-info/metadata.json
aiompd-0.4.0.dist-info/top_level.txt
