Metadata-Version: 2.0
Name: aiompd
Version: 0.4.0
Summary: MPD (Music Player Daemon) client for asyncio
Home-page: https://github.com/zzzsochi/aiompd
Author: Alexander Zelenyak
Author-email: zzz.sochi@gmail.com
License: UNKNOWN
Keywords: mpd,asyncio
Platform: UNKNOWN
Classifier: License :: OSI Approved :: BSD License
Classifier: Operating System :: POSIX
Classifier: Programming Language :: Python :: 3.5
Classifier: Programming Language :: Python :: 3.6
Classifier: Topic :: System :: Networking
Classifier: Topic :: Multimedia :: Sound/Audio
Classifier: Topic :: Software Development :: Libraries :: Python Modules
Classifier: Development Status :: 5 - Production/Stable
